faizata11_pencariansurat/__init__.py
faizata11_pencariansurat/alquran.py
faizata11_pemcariansurat-0.0.1.dist-info/LICENSE
faizata11_pemcariansurat-0.0.1.dist-info/METADATA
faizata11_pemcariansurat-0.0.1.dist-info/WHEEL
faizata11_pemcariansurat-0.0.1.dist-info/top_level.txt
faizata11_pemcariansurat-0.0.1.dist-info/RECORD
