Metadata-Version: 2.1
Name: faizata11-pemcariansurat
Version: 0.0.1
Summary: Negara Informasi Inform Negara
Home-page: https://github.com/zata1412/faizata11_pencariansurat
Author: zataa11
Author-email: <faizata777@gmail.com>
License: MIT
Platform: UNKNOWN
Classifier: Development Status :: 1 - Planning
License-File: LICENSE
